CHANGES.txt
MANIFEST.in
README.txt
setup.py
mutabletuple/__init__.py
mutabletuple/_mutabletuple.py
mutabletuple.egg-info/PKG-INFO
mutabletuple.egg-info/SOURCES.txt
mutabletuple.egg-info/dependency_links.txt
mutabletuple.egg-info/requires.txt
mutabletuple.egg-info/top_level.txt
mutabletuple/tests/__init__.py
mutabletuple/tests/test_mutabletuple.py