Metadata-Version: 1.1
Name: mutabletuple
Version: 0.2
Summary: Similar to namedlist, but with additional features (nested class, recursive merge, etc).
Home-page: https://github.com/nicolasbessou/mutabletuple
Author: Nicolas BESSOU
Author-email: nicolas.bessou@gmail.com
License: MIT
Platform: UNKNOWN
Classifier: Development Status :: 3 - Alpha
Classifier: Intended Audience :: Developers
Classifier: License :: OSI Approved :: MIT License
Classifier: Topic :: Software Development :: Libraries :: Python Modules
Classifier: Programming Language :: Python :: 2.7
Classifier: Programming Language :: Python :: 3.3
